passagemath_gap.dylibs/libreadline.8.1.dylib
passagemath_gap.dylibs/libpari-gmp-tls.dylib
passagemath_gap.dylibs/libgap.8.dylib
passagemath_gap.dylibs/libgmp.10.dylib
passagemath_gap-10.4.28.dist-info/RECORD
passagemath_gap-10.4.28.dist-info/WHEEL
passagemath_gap-10.4.28.dist-info/top_level.txt
passagemath_gap-10.4.28.dist-info/METADATA
sage/all__sagemath_gap.py
sage/combinat/enumeration_mod_permgroup.cpython-311-darwin.so
sage/combinat/enumeration_mod_permgroup.pyx
sage/combinat/all__sagemath_gap.py
sage/combinat/enumeration_mod_permgroup.pxd
sage/combinat/root_system/reflection_group_c.cpython-311-darwin.so
sage/combinat/root_system/reflection_group_element.cpython-311-darwin.so
sage/combinat/root_system/reflection_group_element.pyx
sage/combinat/root_system/weyl_group.py
sage/combinat/root_system/reflection_group_complex.py
sage/combinat/root_system/all__sagemath_gap.py
sage/combinat/root_system/reflection_group_c.pyx
sage/combinat/root_system/reflection_group_element.pxd
sage/combinat/root_system/reflection_group_real.py
sage/ext_data/all__sagemath_gap.py
sage/ext_data/gap/console.g
sage/ext_data/gap/sage.g
sage/groups/libgap_wrapper.cpython-311-darwin.so
sage/groups/libgap_mixin.py
sage/groups/libgap_wrapper.pyx
sage/groups/libgap_morphism.py
sage/groups/all__sagemath_gap.py
sage/groups/galois_group_perm.py
sage/groups/libgap_group.py
sage/groups/libgap_wrapper.pxd
sage/groups/perm_gps/symgp_conjugacy_class.py
sage/groups/perm_gps/permgroup_morphism.py
sage/groups/perm_gps/permgroup.py
sage/groups/perm_gps/cubegroup.py
sage/groups/perm_gps/constructor.py
sage/groups/perm_gps/permutation_groups_catalog.py
sage/groups/perm_gps/permgroup_named.py
sage/groups/perm_gps/all.py
sage/groups/perm_gps/permgroup_element.pxd
sage/groups/perm_gps/permgroup_element.pyx
sage/groups/perm_gps/permgroup_element.cpython-311-darwin.so
sage/groups/perm_gps/partn_ref/all__sagemath_gap.py
sage/groups/perm_gps/partn_ref2/refinement_generic.pyx
sage/groups/perm_gps/partn_ref2/refinement_generic.cpython-311-darwin.so
sage/groups/perm_gps/partn_ref2/all.py
sage/groups/perm_gps/partn_ref2/refinement_generic.pxd
